dual_tape/__init__.py
dual_tape/assembler.py
dual_tape/dual_tape.py
dual_tape/error.py
dual_tape/log.py
dual_tape/vm.py
dual_tape-1.0.2.dist-info/LICENSE
dual_tape-1.0.2.dist-info/METADATA
dual_tape-1.0.2.dist-info/WHEEL
dual_tape-1.0.2.dist-info/entry_points.txt
dual_tape-1.0.2.dist-info/top_level.txt
dual_tape-1.0.2.dist-info/RECORD
