Metadata-Version: 2.1
Name: dual-tape
Version: 1.0.2
Summary: Tape Esolang
Home-page: https://github.com/cmcmarrow/dual_tape
Author: Charles McMarrow
Author-email: Charles.McMarrow.4@gmail.com
License: Apache Software License 2.0
Platform: UNKNOWN
Classifier: Development Status :: 6 - Mature
Classifier: Environment :: Console
Classifier: Intended Audience :: Developers
Classifier: Natural Language :: English
Classifier: Operating System :: Microsoft :: Windows
Classifier: Operating System :: POSIX :: Linux
Classifier: Operating System :: MacOS :: MacOS X
Classifier: Programming Language :: Python :: 3.8
Classifier: Programming Language :: Python :: 3.9
Classifier: Programming Language :: Python :: 3.10
Provides-Extra: dev
Requires-Dist: wheel ; extra == 'dev'
Requires-Dist: twine ; extra == 'dev'
Requires-Dist: pyinstaller ; extra == 'dev'
